Day 11/FSM/moore overlapping/moore_overlapping.v
//1001 over-lappling sequence detector moore model
module moore_overlapping(
input clk,rst,data,
output detected
);

parameter[2:0]s0=0,s1=1,s2=2,s3=3,s4=4;

reg[2:0]state,next; 

always @ (posedge clk)begin
	if(rst)state<=0;
	else state<=next;
end

always @ (*)begin
	case(state)
		s0:next=(data)?s1:s0;
		s1:next=(data)?s1:s2;
		s2:next=(data)?s1:s3;
		s3:next=(data)?s4:s0;
		s4:next=(data)?s1:s2;
		default:next=s0;
	endcase
end
assign detected=(state==s4);
endmodule

Day 11/FSM/moore overlapping/moore_overlapping_tb.v
module moore_overlapping_tb;
reg clk,rst,data;
wire detected;

moore_overlapping dut(.clk(clk),.rst(rst),.data(data),.detected(detected));

initial begin
	$dumpfile("moore_overlapping.vcd");
	$dumpvars(0);

	clk=0;
	
	rst=1;
	data=0;#10

	rst=0;#10

	data=0;#10;
	data=1;#10;
	data=0;#10;
	data=0;#10;
	data=1;#10;
	data=0;#10;
        data=0;#10;
	data=1;#10;  
	data=1;#10;  
	data=1;#10; 
	data=1;#10;
	data=1;#10;  
	$finish;#12;

end

always @(posedge clk)begin
	$display(" | clk = %b | reset = %b | State = %b | data = %b | detected = %b", clk, rst, dut.state, data, detected);
end

always #5 clk=~clk;

endmodule

Day 11/FSM/moore overlapping/moore_overlapping.vcd
$date
	Fri Dec 19 15:35:15 2025
$end
$version
	Icarus Verilog
$end
$timescale
	1s
$end
$scope module moore_overlapping_tb $end
$var wire 1 ! detected $end
$var reg 1 " clk $end
$var reg 1 # data $end
$var reg 1 $ rst $end
$scope module dut $end
$var wire 1 " clk $end
$var wire 1 # data $end
$var wire 1 $ rst $end
$var wire 1 ! detected $end
$var parameter 3 % s0 $end
$var parameter 3 & s1 $end
$var parameter 3 ' s2 $end
$var parameter 3 ( s3 $end
$var parameter 3 ) s4 $end
$var reg 3 * next [2:0] $end
$var reg 3 + state [2:0] $end
$upscope $end
$upscope $end
$enddefinitions $end
$comment Show the parameter values. $end
$dumpall
b100 )
b11 (
b10 '
b1 &
b0 %
$end
#0
$dumpvars
bx +
b0 *
1$
0#
0"
x!
$end
#5
0!
b0 +
1"
#10
0"
0$
#15
1"
#20
0"
#25
1"
#30
b1 *
0"
1#
#35
b1 +
1"
#40
b10 *
0"
0#
#45
b11 *
b10 +
1"
#50
0"
#55
b0 *
b11 +
1"
#60
b100 *
0"
1#
#65
b1 *
1!
b100 +
1"
#70
b10 *
0"
0#
#75
b11 *
0!
b10 +
1"
#80
0"
#85
b0 *
b11 +
1"
#90
b100 *
0"
1#
#95
b1 *
1!
b100 +
1"
#100
0"
#105
0!
b1 +
1"
