day 5/mux_ps.v
module mux8(input [7:0]data,input [2:0]select,output y);
assign y=data[select];
endmodule

day 5/8x1 mux using part select/mux8_tb.v
module mux8_tb;
reg  [7:0] data;
reg  [2:0] select;
wire y;
mux8 dut (.data(data),.select(select),.y(y));
initial begin
    $dumpfile("mux8.vcd");
    $dumpvars(0);
    data= 8'b10110110; 

    select = 3'd0; #10;
    select = 3'd1; #10;
    select = 3'd2; #10;
    select = 3'd3; #10;
    select = 3'd4; #10;
    select = 3'd5; #10;
    select = 3'd6; #10;
    select = 3'd7; #10;
    $finish;
end
initial begin
    $monitor("Time=%0t | d=%b | sel=%0d | y=%b",$time, data, select, y);
end
endmodule

day 5/8x1 mux using part select/mux8.vcd
$date
	Fri Dec  5 18:06:53 2025
$end
$version
	Icarus Verilog
$end
$timescale
	1s
$end
$scope module mux8_tb $end
$var wire 1 ! y $end
$var reg 8 " data [7:0] $end
$var reg 3 # select [2:0] $end
$scope module dut $end
$var wire 8 $ data [7:0] $end
$var wire 3 % select [2:0] $end
$var wire 1 ! y $end
$upscope $end
$upscope $end
$enddefinitions $end
$comment Show the parameter values. $end
$dumpall
$end
#0
$dumpvars
b0 %
b10110110 $
b0 #
b10110110 "
0!
$end
#10
1!
b1 #
b1 %
#20
b10 #
b10 %
#30
0!
b11 #
b11 %
#40
1!
b100 #
b100 %
#50
b101 #
b101 %
#60
0!
b110 #
b110 %
#70
1!
b111 #
b111 %
