Day 10/counter/gray counter/gray_counter.v
module gray_counter (
    input clk,
    input rst,
    output reg [3:0] gray
);

reg [3:0] bin;

always @(posedge clk) begin
    if (rst)
        bin <= 4'b0000;
    else
        bin <= bin + 1'b1;
end

always @(*) begin
    gray = bin ^ (bin >> 1);
end

endmodule

Day 10/counter/gray counter/gray_counter_tb.v
module gray_counter_tb;
reg clk,rst;
wire [3:0]gray;
gray_counter dut(.clk(clk),.rst(rst),.gray(gray));
initial begin
	$monitor("clock = %d | reset = %d | count = %d | time = %0t |",clk,rst,gray,$time);
	$dumpfile("gray_counter.vcd");
	$dumpvars(0);

	clk=0;rst=1;#10;


	rst=0;#160
	$finish;

end
always #5 clk=~clk;
endmodule

Day 10/counter/gray counter/gray_counter.vcd
$date
	Thu Dec 18 12:47:33 2025
$end
$version
	Icarus Verilog
$end
$timescale
	1s
$end
$scope module gray_counter_tb $end
$var wire 4 ! gray [3:0] $end
$var reg 1 " clk $end
$var reg 1 # rst $end
$scope module dut $end
$var wire 1 " clk $end
$var wire 1 # rst $end
$var reg 4 $ bin [3:0] $end
$var reg 4 % gray [3:0] $end
$upscope $end
$upscope $end
$enddefinitions $end
$comment Show the parameter values. $end
$dumpall
$end
#0
$dumpvars
bx %
bx $
1#
0"
bx !
$end
#5
b0 !
b0 %
b0 $
1"
#10
0"
0#
#15
b1 !
b1 %
b1 $
1"
#20
0"
#25
b11 !
b11 %
b10 $
1"
#30
0"
#35
b10 !
b10 %
b11 $
1"
#40
0"
#45
b110 !
b110 %
b100 $
1"
#50
0"
#55
b111 !
b111 %
b101 $
1"
#60
0"
#65
b101 !
b101 %
b110 $
1"
#70
0"
#75
b100 !
b100 %
b111 $
1"
#80
0"
#85
b1100 !
b1100 %
b1000 $
1"
#90
0"
#95
b1101 !
b1101 %
b1001 $
1"
#100
0"
#105
b1111 !
b1111 %
b1010 $
1"
#110
0"
#115
b1110 !
b1110 %
b1011 $
1"
#120
0"
#125
b1010 !
b1010 %
b1100 $
1"
#130
0"
#135
b1011 !
b1011 %
b1101 $
1"
#140
0"
#145
b1001 !
b1001 %
b1110 $
1"
#150
0"
#155
b1000 !
b1000 %
b1111 $
1"
#160
0"
#165
b0 !
b0 %
b0 $
1"
