Day 07/palindrome/palindrome.v
module palindrome(
input  [15:0] num,
output reg    pal
);
reg [3:0] d1, d2, d3, d4;
always @(*) begin
    d1 = (num / 1000) % 10;
    d2 = (num / 100)  % 10;
    d3 = (num / 10)   % 10;
    d4 =  num % 10;
    if (d1 == d4 && d2 == d3)
        pal = 1;
    else
        pal = 0;
end
endmodule

Day 7/mathematical logic/palindrome/palindrome_tb.v
module palindrome_tb;
reg  [15:0] num;
wire pal;
palindrome dut (.num(num),.pal(pal));
integer i;
initial begin
    $dumpfile("palindrome.vcd");
    $dumpvars(0);
    for (i = 1000; i <= 9999; i = i + 1) begin
        num = i;#1;
    end
$finish;
end
initial begin
    $monitor("Time=%0t | num=%0d | pal=%b", $time, num, pal);
end
endmodule

Day 7/mathematical logic/palindrome/palindrome.vcd
$date
	Mon Dec  8 14:38:00 2025
$end
$version
	Icarus Verilog
$end
$timescale
	1s
$end
$scope module palindrome_tb $end
$var wire 1 ! pal $end
$var reg 16 " num [15:0] $end
$var integer 32 # i [31:0] $end
$scope module dut $end
$var wire 16 $ num [15:0] $end
$var reg 4 % d1 [3:0] $end
$var reg 4 & d2 [3:0] $end
$var reg 4 ' d3 [3:0] $end
$var reg 4 ( d4 [3:0] $end
$var reg 1 ! pal $end
$upscope $end
$upscope $end
$enddefinitions $end
$comment Show the parameter values. $end
$dumpall
$end
#0
$dumpvars
b0 (
b0 '
b0 &
b1 %
b1111101000 $
b1111101000 #
b1111101000 "
0!
$end
#1
1!
b1 (
b1111101001 "
b1111101001 $
b1111101001 #
#2
0!
b10 (
b1111101010 "
b1111101010 $
b1111101010 #
#3
b11 (
b1111101011 "
b1111101011 $
b1111101011 #
#4
b100 (
b1111101100 "
b1111101100 $
b1111101100 #
#5
b101 (
b1111101101 "
b1111101101 $
b1111101101 #
#6
b110 (
b1111101110 "
b1111101110 $
b1111101110 #
#7
b111 (
b1111101111 "
b1111101111 $
b1111101111 #
#8
b1000 (
b1111110000 "
b1111110000 $
b1111110000 #
#9
b1001 (
b1111110001 "
b1111110001 $
b1111110001 #
#10
b0 (
b1 '
b1111110010 "
b1111110010 $
b1111110010 #
#11
b1 (
b1111110011 "
b1111110011 $
b1111110011 #
#12
b10 (
b1111110100 "
b1111110100 $
b1111110100 #
#13
b11 (
b1111110101 "
b1111110101 $
b1111110101 #
#14
b100 (
b1111110110 "
b1111110110 $
b1111110110 #
#15
b101 (
b1111110111 "
b1111110111 $
b1111110111 #
#16
b110 (
b1111111000 "
b1111111000 $
b1111111000 #
#17
b111 (
b1111111001 "
b1111111001 $
b1111111001 #
#18
b1000 (
b1111111010 "
b1111111010 $
b1111111010 #
#19
b1001 (
b1111111011 "
b1111111011 $
b1111111011 #
#20
b0 (
b10 '
b1111111100 "
b1111111100 $
b1111111100 #
#21
b1 (
b1111111101 "
b1111111101 $
b1111111101 #
#22
b10 (
b1111111110 "
b1111111110 $
b1111111110 #
#23
b11 (
b1111111111 "
b1111111111 $
b1111111111 #
#24
b100 (
b10000000000 "
b10000000000 $
b10000000000 #
#25
b101 (
b10000000001 "
b10000000001 $
b10000000001 #
#26
b110 (
b10000000010 "
b10000000010 $
b10000000010 #
#27
b111 (
b10000000011 "
b10000000011 $
b10000000011 #
#28
b1000 (
b10000000100 "
b10000000100 $
b10000000100 #
#29
b1001 (
b10000000101 "
b10000000101 $
b10000000101 #
#30
b0 (
b11 '
b10000000110 "
b10000000110 $
b10000000110 #
#31
b1 (
b10000000111 "
b10000000111 $
b10000000111 #
#32
b10 (
b10000001000 "
b10000001000 $
b10000001000 #
#33
b11 (
b10000001001 "
b10000001001 $
b10000001001 #
#34
b100 (
b10000001010 "
b10000001010 $
b10000001010 #
#35
b101 (
b10000001011 "
b10000001011 $
b10000001011 #
#36
b110 (
b10000001100 "
b10000001100 $
b10000001100 #
#37
b111 (
b10000001101 "
b10000001101 $
b10000001101 #
#38
b1000 (
b10000001110 "
b10000001110 $
b10000001110 #
#39
b1001 (
b10000001111 "
b10000001111 $
b10000001111 #
#40
b0 (
b100 '
b10000010000 "
b10000010000 $
b10000010000 #
#41
b1 (
b10000010001 "
b10000010001 $
b10000010001 #
#42
b10 (
b10000010010 "
b10000010010 $
b10000010010 #
#43
b11 (
b10000010011 "
b10000010011 $
b10000010011 #
#44
b100 (
b10000010100 "
b10000010100 $
b10000010100 #
#45
b101 (
b10000010101 "
b10000010101 $
b10000010101 #
#46
b110 (
b10000010110 "
b10000010110 $
b10000010110 #
#47
b111 (
b10000010111 "
b10000010111 $
b10000010111 #
#48
b1000 (
b10000011000 "
b10000011000 $
b10000011000 #
#49
b1001 (
b10000011001 "
b10000011001 $
b10000011001 #
#50
b0 (
b101 '
b10000011010 "
b10000011010 $
b10000011010 #
#51
b1 (
b10000011011 "
b10000011011 $
b10000011011 #
#52
b10 (
b10000011100 "
b10000011100 $
b10000011100 #
#53
b11 (
b10000011101 "
b10000011101 $
b10000011101 #
#54
b100 (
b10000011110 "
b10000011110 $
b10000011110 #
#55
b101 (
b10000011111 "
b10000011111 $
b10000011111 #
#56
b110 (
b10000100000 "
b10000100000 $
b10000100000 #
#57
b111 (
b10000100001 "
b10000100001 $
b10000100001 #
#58
b1000 (
b10000100010 "
b10000100010 $
b10000100010 #
#59
b1001 (
b10000100011 "
b10000100011 $
b10000100011 #
#60
b0 (
b110 '
b10000100100 "
b10000100100 $
b10000100100 #
#61
b1 (
b10000100101 "
b10000100101 $
b10000100101 #
#62
b10 (
b10000100110 "
b10000100110 $
b10000100110 #
#63
b11 (
b10000100111 "
b10000100111 $
b10000100111 #
#64
b100 (
b10000101000 "
b10000101000 $
b10000101000 #
#65
b101 (
b10000101001 "
b10000101001 $
b10000101001 #
#66
b110 (
b10000101010 "
b10000101010 $
b10000101010 #
#67
b111 (
b10000101011 "
b10000101011 $
b10000101011 #
#68
b1000 (
b10000101100 "
b10000101100 $
b10000101100 #
#69
b1001 (
b10000101101 "
b10000101101 $
b10000101101 #
#70
b0 (
b111 '
b10000101110 "
b10000101110 $
b10000101110 #
#71
b1 (
b10000101111 "
b10000101111 $
b10000101111 #
#72
b10 (
b10000110000 "
b10000110000 $
b10000110000 #
#73
b11 (
b10000110001 "
b10000110001 $
b10000110001 #
#74
b100 (
b10000110010 "
b10000110010 $
b10000110010 #
#75
b101 (
b10000110011 "
b10000110011 $
b10000110011 #
#76
b110 (
b10000110100 "
b10000110100 $
b10000110100 #
#77
b111 (
b10000110101 "
b10000110101 $
b10000110101 #
#78
b1000 (
b10000110110 "
b10000110110 $
b10000110110 #
#79
b1001 (
b10000110111 "
b10000110111 $
b10000110111 #
#80
b0 (
b1000 '
b10000111000 "
b10000111000 $
b10000111000 #
#81
b1 (
b10000111001 "
b10000111001 $
b10000111001 #
#82
b10 (
b10000111010 "
b10000111010 $
b10000111010 #
#83
b11 (
b10000111011 "
b10000111011 $
b10000111011 #
#84
b100 (
b10000111100 "
b10000111100 $
b10000111100 #
#85
b101 (
b10000111101 "
b10000111101 $
b10000111101 #
#86
b110 (
b10000111110 "
b10000111110 $
b10000111110 #
#87
b111 (
b10000111111 "
b10000111111 $
b10000111111 #
#88
b1000 (
b10001000000 "
b10001000000 $
b10001000000 #
#89
b1001 (
b10001000001 "
b10001000001 $
b10001000001 #
#90
b0 (
b1001 '
b10001000010 "
b10001000010 $
b10001000010 #
#91
b1 (
b10001000011 "
b10001000011 $
b10001000011 #
#92
b10 (
b10001000100 "
b10001000100 $
b10001000100 #
#93
b11 (
b10001000101 "
b10001000101 $
b10001000101 #
#94
b100 (
b10001000110 "
b10001000110 $
b10001000110 #
#95
b101 (
b10001000111 "
b10001000111 $
b10001000111 #
#96
b110 (
b10001001000 "
b10001001000 $
b10001001000 #
#97
b111 (
b10001001001 "
b10001001001 $
b10001001001 #
#98
b1000 (
b10001001010 "
b10001001010 $
b10001001010 #
#99
b1001 (
b10001001011 "
b10001001011 $
b10001001011 #
#100
b0 (
b0 '
b1 &
b10001001100 "
b10001001100 $
b10001001100 #
#101
b1 (
b10001001101 "
b10001001101 $
b10001001101 #
#102
b10 (
b10001001110 "
b10001001110 $
b10001001110 #
#103
b11 (
b10001001111 "
b10001001111 $
b10001001111 #
#104
b100 (
b10001010000 "
b10001010000 $
b10001010000 #
#105
b101 (
b10001010001 "
b10001010001 $
b10001010001 #
#106
b110 (
b10001010010 "
b10001010010 $
b10001010010 #
#107
b111 (
b10001010011 "
b10001010011 $
b10001010011 #
#108
b1000 (
b10001010100 "
b10001010100 $
b10001010100 #
#109
b1001 (
b10001010101 "
b10001010101 $
b10001010101 #
#110
b0 (
b1 '
b10001010110 "
b10001010110 $
b10001010110 #
#111
1!
b1 (
b10001010111 "
b10001010111 $
b10001010111 #
#112
0!
b10 (
b10001011000 "
b10001011000 $
b10001011000 #
#113
b11 (
b10001011001 "
b10001011001 $
b10001011001 #
#114
b100 (
b10001011010 "
b10001011010 $
b10001011010 #
#115
b101 (
b10001011011 "
b10001011011 $
b10001011011 #
#116
b110 (
b10001011100 "
b10001011100 $
b10001011100 #
#117
b111 (
b10001011101 "
b10001011101 $
b10001011101 #
#118
b1000 (
b10001011110 "
b10001011110 $
b10001011110 #
#119
b1001 (
b10001011111 "
b10001011111 $
b10001011111 #
#120
b0 (
b10 '
b10001100000 "
b10001100000 $
b10001100000 #
#121
b1 (
b10001100001 "
b10001100001 $
b10001100001 #
#122
b10 (
b10001100010 "
b10001100010 $
b10001100010 #
#123
b11 (
b10001100011 "
b10001100011 $
b10001100011 #
#124
b100 (
b10001100100 "
b10001100100 $
b10001100100 #
#125
b101 (
b10001100101 "
b10001100101 $
b10001100101 #
#126
b110 (
b10001100110 "
b10001100110 $
b10001100110 #
#127
b111 (
b10001100111 "
b10001100111 $
b10001100111 #
#128
b1000 (
b10001101000 "
b10001101000 $
b10001101000 #
#129
b1001 (
b10001101001 "
b10001101001 $
b10001101001 #
#130
b0 (
b11 '
b10001101010 "
b10001101010 $
b10001101010 #
#131
b1 (
b10001101011 "
b10001101011 $
b10001101011 #
#132
b10 (
b10001101100 "
b10001101100 $
b10001101100 #
#133
b11 (
b10001101101 "
b10001101101 $
b10001101101 #
#134
b100 (
b10001101110 "
b10001101110 $
b10001101110 #
#135
b101 (
b10001101111 "
b10001101111 $
b10001101111 #
#136
b110 (
b10001110000 "
b10001110000 $
b10001110000 #
#137
b111 (
b10001110001 "
b10001110001 $
b10001110001 #
#138
b1000 (
b10001110010 "
b10001110010 $
b10001110010 #
#139
b1001 (
b10001110011 "
b10001110011 $
b10001110011 #
#140
b0 (
b100 '
b10001110100 "
b10001110100 $
b10001110100 #
#141
b1 (
b10001110101 "
b10001110101 $
b10001110101 #
#142
b10 (
b10001110110 "
b10001110110 $
b10001110110 #
#143
b11 (
b10001110111 "
b10001110111 $
b10001110111 #
#144
b100 (
b10001111000 "
b10001111000 $
b10001111000 #
#145
b101 (
b10001111001 "
b10001111001 $
b10001111001 #
#146
b110 (
b10001111010 "
b10001111010 $
b10001111010 #
#147
b111 (
b10001111011 "
b10001111011 $
b10001111011 #
#148
b1000 (
b10001111100 "
b10001111100 $
b10001111100 #
#149
b1001 (
b10001111101 "
b10001111101 $
b10001111101 #
#150
b0 (
b101 '
b10001111110 "
b10001111110 $
b10001111110 #
#151
b1 (
b10001111111 "
b10001111111 $
b10001111111 #
#152
b10 (
b10010000000 "
b10010000000 $
b10010000000 #
#153
b11 (
b10010000001 "
b10010000001 $
b10010000001 #
#154
b100 (
b10010000010 "
b10010000010 $
b10010000010 #
#155
b101 (
b10010000011 "
b10010000011 $
b10010000011 #
#156
b110 (
b10010000100 "
b10010000100 $
b10010000100 #
#157
b111 (
b10010000101 "
b10010000101 $
b10010000101 #
#158
b1000 (
b10010000110 "
b10010000110 $
b10010000110 #
#159
b1001 (
b10010000111 "
b10010000111 $
b10010000111 #
#160
b0 (
b110 '
b10010001000 "
b10010001000 $
b10010001000 #
#161
b1 (
b10010001001 "
b10010001001 $
b10010001001 #
#162
b10 (
b10010001010 "
b10010001010 $
b10010001010 #
#163
b11 (
b10010001011 "
b10010001011 $
b10010001011 #
#164
b100 (
b10010001100 "
b10010001100 $
b10010001100 #
#165
b101 (
b10010001101 "
b10010001101 $
b10010001101 #
#166
b110 (
b10010001110 "
b10010001110 $
b10010001110 #
#167
b111 (
b10010001111 "
b10010001111 $
b10010001111 #
#168
b1000 (
b10010010000 "
b10010010000 $
b10010010000 #
#169
b1001 (
b10010010001 "
b10010010001 $
b10010010001 #
#170
b0 (
b111 '
b10010010010 "
b10010010010 $
b10010010010 #
#171
b1 (
b10010010011 "
b10010010011 $
b10010010011 #
#172
b10 (
b10010010100 "
b10010010100 $
b10010010100 #
#173
b11 (
b10010010101 "
b10010010101 $
b10010010101 #
#174
b100 (
b10010010110 "
b10010010110 $
b10010010110 #
#175
b101 (
b10010010111 "
b10010010111 $
b10010010111 #
#176
b110 (
b10010011000 "
b10010011000 $
b10010011000 #
#177
b111 (
b10010011001 "
b10010011001 $
b10010011001 #
#178
b1000 (
b10010011010 "
b10010011010 $
b10010011010 #
#179
b1001 (
b10010011011 "
b10010011011 $
b10010011011 #
#180
b0 (
b1000 '
b10010011100 "
b10010011100 $
b10010011100 #
#181
b1 (
b10010011101 "
b10010011101 $
b10010011101 #
#182
b10 (
b10010011110 "
b10010011110 $
b10010011110 #
#183
b11 (
b10010011111 "
b10010011111 $
b10010011111 #
#184
b100 (
b10010100000 "
b10010100000 $
b10010100000 #
#185
b101 (
b10010100001 "
b10010100001 $
b10010100001 #
#186
b110 (
b10010100010 "
b10010100010 $
b10010100010 #
#187
b111 (
b10010100011 "
b10010100011 $
b10010100011 #
#188
b1000 (
b10010100100 "
b10010100100 $
b10010100100 #
#189
b1001 (
b10010100101 "
b10010100101 $
b10010100101 #
#190
b0 (
b1001 '
b10010100110 "
b10010100110 $
b10010100110 #
#191
b1 (
b10010100111 "
b10010100111 $
b10010100111 #
#192
b10 (
b10010101000 "
b10010101000 $
b10010101000 #
#193
b11 (
b10010101001 "
b10010101001 $
b10010101001 #
#194
b100 (
b10010101010 "
b10010101010 $
b10010101010 #
#195
b101 (
b10010101011 "
b10010101011 $
b10010101011 #
#196
b110 (
b10010101100 "
b10010101100 $
b10010101100 #
#197
b111 (
b10010101101 "
b10010101101 $
b10010101101 #
#198
b1000 (
b10010101110 "
b10010101110 $
b10010101110 #
#199
b1001 (
b10010101111 "
b10010101111 $
b10010101111 #
#200
b0 (
b0 '
b10 &
b10010110000 "
b10010110000 $
b10010110000 #
#201
b1 (
b10010110001 "
b10010110001 $
b10010110001 #
#202
b10 (
b10010110010 "
b10010110010 $
b10010110010 #
#203
b11 (
b10010110011 "
b10010110011 $
b10010110011 #
#204
b100 (
b10010110100 "
b10010110100 $
b10010110100 #
#205
b101 (
b10010110101 "
b10010110101 $
b10010110101 #
#206
b110 (
b10010110110 "
b10010110110 $
b10010110110 #
#207
b111 (
b10010110111 "
b10010110111 $
b10010110111 #
#208
b1000 (
b10010111000 "
b10010111000 $
b10010111000 #
#209
b1001 (
b10010111001 "
b10010111001 $
b10010111001 #
#210
b0 (
b1 '
b10010111010 "
b10010111010 $
b10010111010 #
#211
b1 (
b10010111011 "
b10010111011 $
b10010111011 #
#212
b10 (
b10010111100 "
b10010111100 $
b10010111100 #
#213
b11 (
b10010111101 "
b10010111101 $
b10010111101 #
#214
b100 (
b10010111110 "
b10010111110 $
b10010111110 #
#215
b101 (
b10010111111 "
b10010111111 $
b10010111111 #
#216
b110 (
b10011000000 "
b10011000000 $
b10011000000 #
#217
b111 (
b10011000001 "
b10011000001 $
b10011000001 #
#218
b1000 (
b10011000010 "
b10011000010 $
b10011000010 #
#219
b1001 (
b10011000011 "
b10011000011 $
b10011000011 #
#220
b0 (
b10 '
b10011000100 "
b10011000100 $
b10011000100 #
#221
1!
b1 (
b10011000101 "
b10011000101 $
b10011000101 #
#222
0!
b10 (
b10011000110 "
b10011000110 $
b10011000110 #
#223
b11 (
b10011000111 "
b10011000111 $
b10011000111 #
#224
b100 (
b10011001000 "
b10011001000 $
b10011001000 #
#225
b101 (
b10011001001 "
b10011001001 $
b10011001001 #
#226
b110 (
b10011001010 "
b10011001010 $
b10011001010 #
#227
b111 (
b10011001011 "
b10011001011 $
b10011001011 #
#228
b1000 (
b10011001100 "
b10011001100 $
b10011001100 #
#229
b1001 (
b10011001101 "
b10011001101 $
b10011001101 #
#230
b0 (
b11 '
b10011001110 "
b10011001110 $
b10011001110 #
#231
b1 (
b10011001111 "
b10011001111 $
b10011001111 #
#232
b10 (
b10011010000 "
b10011010000 $
b10011010000 #
#233
b11 (
b10011010001 "
b10011010001 $
b10011010001 #
#234
b100 (
b10011010010 "
b10011010010 $
b10011010010 #
#235
b101 (
b10011010011 "
b10011010011 $
b10011010011 #
#236
b110 (
b10011010100 "
b10011010100 $
b10011010100 #
#237
b111 (
b10011010101 "
b10011010101 $
b10011010101 #
#238
b1000 (
b10011010110 "
b10011010110 $
b10011010110 #
#239
b1001 (
b10011010111 "
b10011010111 $
b10011010111 #
#240
b0 (
b100 '
b10011011000 "
b10011011000 $
b10011011000 #
#241
b1 (
b10011011001 "
b10011011001 $
b10011011001 #
#242
b10 (
b10011011010 "
b10011011010 $
b10011011010 #
#243
b11 (
b10011011011 "
b10011011011 $
b10011011011 #
#244
b100 (
b10011011100 "
b10011011100 $
b10011011100 #
#245
b101 (
b10011011101 "
b10011011101 $
b10011011101 #
#246
b110 (
b10011011110 "
b10011011110 $
b10011011110 #
#247
b111 (
b10011011111 "
b10011011111 $
b10011011111 #
#248
b1000 (
b10011100000 "
b10011100000 $
b10011100000 #
#249
b1001 (
b10011100001 "
b10011100001 $
b10011100001 #
#250
b0 (
b101 '
b10011100010 "
b10011100010 $
b10011100010 #
#251
b1 (
b10011100011 "
b10011100011 $
b10011100011 #
#252
b10 (
b10011100100 "
b10011100100 $
b10011100100 #
#253
b11 (
b10011100101 "
b10011100101 $
b10011100101 #
#254
b100 (
b10011100110 "
b10011100110 $
b10011100110 #
#255
b101 (
b10011100111 "
b10011100111 $
b10011100111 #
#256
b110 (
b10011101000 "
b10011101000 $
b10011101000 #
#257
b111 (
b10011101001 "
b10011101001 $
b10011101001 #
#258
b1000 (
b10011101010 "
b10011101010 $
b10011101010 #
#259
b1001 (
b10011101011 "
b10011101011 $
b10011101011 #
#260
b0 (
b110 '
b10011101100 "
b10011101100 $
b10011101100 #
#261
b1 (
b10011101101 "
b10011101101 $
b10011101101 #
#262
b10 (
b10011101110 "
b10011101110 $
b10011101110 #
#263
b11 (
b10011101111 "
b10011101111 $
b10011101111 #
#264
b100 (
b10011110000 "
b10011110000 $
b10011110000 #
#265
b101 (
b10011110001 "
b10011110001 $
b10011110001 #
#266
b110 (
b10011110010 "
b10011110010 $
b10011110010 #
#267
b111 (
b10011110011 "
b10011110011 $
b10011110011 #
#268
b1000 (
b10011110100 "
b10011110100 $
b10011110100 #
#269
b1001 (
b10011110101 "
b10011110101 $
b10011110101 #
#270
b0 (
b111 '
b10011110110 "
b10011110110 $
b10011110110 #
#271
b1 (
b10011110111 "
b10011110111 $
b10011110111 #
#272
b10 (
b10011111000 "
b10011111000 $
b10011111000 #
#273
b11 (
b10011111001 "
b10011111001 $
b10011111001 #
#274
b100 (
b10011111010 "
b10011111010 $
b10011111010 #
#275
b101 (
b10011111011 "
b10011111011 $
b10011111011 #
#276
b110 (
b10011111100 "
b10011111100 $
b10011111100 #
#277
b111 (
b10011111101 "
b10011111101 $
b10011111101 #
#278
b1000 (
b10011111110 "
b10011111110 $
b10011111110 #
#279
b1001 (
b10011111111 "
b10011111111 $
b10011111111 #
#280
b0 (
b1000 '
b10100000000 "
b10100000000 $
b10100000000 #
#281
b1 (
b10100000001 "
b10100000001 $
b10100000001 #
#282
b10 (
b10100000010 "
b10100000010 $
b10100000010 #
#283
b11 (
b10100000011 "
b10100000011 $
b10100000011 #
#284
b100 (
b10100000100 "
b10100000100 $
b10100000100 #
#285
b101 (
b10100000101 "
b10100000101 $
b10100000101 #
#286
b110 (
b10100000110 "
b10100000110 $
b10100000110 #
#287
b111 (
b10100000111 "
b10100000111 $
b10100000111 #
#288
b1000 (
b10100001000 "
b10100001000 $
b10100001000 #
#289
b1001 (
b10100001001 "
b10100001001 $
b10100001001 #
#290
b0 (
b1001 '
b10100001010 "
b10100001010 $
b10100001010 #
#291
b1 (
b10100001011 "
b10100001011 $
b10100001011 #
#292
b10 (
b10100001100 "
b10100001100 $
b10100001100 #
#293
b11 (
b10100001101 "
b10100001101 $
b10100001101 #
#294
b100 (
b10100001110 "
b10100001110 $
b10100001110 #
#295
b101 (
b10100001111 "
b10100001111 $
b10100001111 #
#296
b110 (
b10100010000 "
b10100010000 $
b10100010000 #
#297
b111 (
b10100010001 "
b10100010001 $
b10100010001 #
#298
b1000 (
b10100010010 "
b10100010010 $
b10100010010 #
#299
b1001 (
b10100010011 "
b10100010011 $
b10100010011 #
#300
b0 (
b0 '
b11 &
b10100010100 "
b10100010100 $
b10100010100 #
#301
b1 (
b10100010101 "
b10100010101 $
b10100010101 #
#302
b10 (
b10100010110 "
b10100010110 $
b10100010110 #
#303
b11 (
b10100010111 "
b10100010111 $
b10100010111 #
#304
b100 (
b10100011000 "
b10100011000 $
b10100011000 #
#305
b101 (
b10100011001 "
b10100011001 $
b10100011001 #
#306
b110 (
b10100011010 "
b10100011010 $
b10100011010 #
#307
b111 (
b10100011011 "
b10100011011 $
b10100011011 #
#308
b1000 (
b10100011100 "
b10100011100 $
b10100011100 #
#309
b1001 (
b10100011101 "
b10100011101 $
b10100011101 #
#310
b0 (
b1 '
b10100011110 "
b10100011110 $
b10100011110 #
#311
b1 (
b10100011111 "
b10100011111 $
b10100011111 #
#312
b10 (
b10100100000 "
b10100100000 $
b10100100000 #
#313
b11 (
b10100100001 "
b10100100001 $
b10100100001 #
#314
b100 (
b10100100010 "
b10100100010 $
b10100100010 #
#315
b101 (
b10100100011 "
b10100100011 $
b10100100011 #
#316
b110 (
b10100100100 "
b10100100100 $
b10100100100 #
#317
b111 (
b10100100101 "
b10100100101 $
b10100100101 #
#318
b1000 (
b10100100110 "
b10100100110 $
b10100100110 #
#319
b1001 (
b10100100111 "
b10100100111 $
b10100100111 #
#320
b0 (
b10 '
b10100101000 "
b10100101000 $
b10100101000 #
#321
b1 (
b10100101001 "
b10100101001 $
b10100101001 #
#322
b10 (
b10100101010 "
b10100101010 $
b10100101010 #
#323
b11 (
b10100101011 "
b10100101011 $
b10100101011 #
#324
b100 (
b10100101100 "
b10100101100 $
b10100101100 #
#325
b101 (
b10100101101 "
b10100101101 $
b10100101101 #
#326
b110 (
b10100101110 "
b10100101110 $
b10100101110 #
#327
b111 (
b10100101111 "
b10100101111 $
b10100101111 #
#328
b1000 (
b10100110000 "
b10100110000 $
b10100110000 #
#329
b1001 (
b10100110001 "
b10100110001 $
b10100110001 #
#330
b0 (
b11 '
b10100110010 "
b10100110010 $
b10100110010 #
#331
1!
b1 (
b10100110011 "
b10100110011 $
b10100110011 #
#332
0!
b10 (
b10100110100 "
b10100110100 $
b10100110100 #
#333
b11 (
b10100110101 "
b10100110101 $
b10100110101 #
#334
b100 (
b10100110110 "
b10100110110 $
b10100110110 #
#335
b101 (
b10100110111 "
b10100110111 $
b10100110111 #
#336
b110 (
b10100111000 "
b10100111000 $
b10100111000 #
#337
b111 (
b10100111001 "
b10100111001 $
b10100111001 #
#338
b1000 (
b10100111010 "
b10100111010 $
b10100111010 #
#339
b1001 (
b10100111011 "
b10100111011 $
b10100111011 #
#340
b0 (
b100 '
b10100111100 "
b10100111100 $
b10100111100 #
#341
b1 (
b10100111101 "
b10100111101 $
b10100111101 #
#342
b10 (
b10100111110 "
b10100111110 $
b10100111110 #
#343
b11 (
b10100111111 "
b10100111111 $
b10100111111 #
#344
b100 (
b10101000000 "
b10101000000 $
b10101000000 #
#345
b101 (
b10101000001 "
b10101000001 $
b10101000001 #
#346
b110 (
b10101000010 "
b10101000010 $
b10101000010 #
#347
b111 (
b10101000011 "
b10101000011 $
b10101000011 #
#348
b1000 (
b10101000100 "
b10101000100 $
b10101000100 #
#349
b1001 (
b10101000101 "
b10101000101 $
b10101000101 #
#350
b0 (
b101 '
b10101000110 "
b10101000110 $
b10101000110 #
#351
b1 (
b10101000111 "
b10101000111 $
b10101000111 #
#352
b10 (
b10101001000 "
b10101001000 $
b10101001000 #
#353
b11 (
b10101001001 "
b10101001001 $
b10101001001 #
#354
b100 (
b10101001010 "
b10101001010 $
b10101001010 #
#355
b101 (
b10101001011 "
b10101001011 $
b10101001011 #
#356
b110 (
b10101001100 "
b10101001100 $
b10101001100 #
#357
b111 (
b10101001101 "
b10101001101 $
b10101001101 #
#358
b1000 (
b10101001110 "
b10101001110 $
b10101001110 #
#359
b1001 (
b10101001111 "
b10101001111 $
b10101001111 #
#360
b0 (
b110 '
b10101010000 "
b10101010000 $
b10101010000 #
#361
b1 (
b10101010001 "
b10101010001 $
b10101010001 #
#362
b10 (
b10101010010 "
b10101010010 $
b10101010010 #
#363
b11 (
b10101010011 "
b10101010011 $
b10101010011 #
#364
b100 (
b10101010100 "
b10101010100 $
b10101010100 #
#365
b101 (
b10101010101 "
b10101010101 $
b10101010101 #
#366
b110 (
b10101010110 "
b10101010110 $
b10101010110 #
#367
b111 (
b10101010111 "
b10101010111 $
b10101010111 #
#368
b1000 (
b10101011000 "
b10101011000 $
b10101011000 #
#369
b1001 (
b10101011001 "
b10101011001 $
b10101011001 #
#370
b0 (
b111 '
b10101011010 "
b10101011010 $
b10101011010 #
#371
b1 (
b10101011011 "
b10101011011 $
b10101011011 #
#372
b10 (
b10101011100 "
b10101011100 $
b10101011100 #
#373
b11 (
b10101011101 "
b10101011101 $
b10101011101 #
#374
b100 (
b10101011110 "
b10101011110 $
b10101011110 #
#375
b101 (
b10101011111 "
b10101011111 $
b10101011111 #
#376
b110 (
b10101100000 "
b10101100000 $
b10101100000 #
#377
b111 (
b10101100001 "
b10101100001 $
b10101100001 #
#378
b1000 (
b10101100010 "
b10101100010 $
b10101100010 #
#379
b1001 (
b10101100011 "
b10101100011 $
b10101100011 #
#380
b0 (
b1000 '
b10101100100 "
b10101100100 $
b10101100100 #
#381
b1 (
b10101100101 "
b10101100101 $
b10101100101 #
#382
b10 (
b10101100110 "
b10101100110 $
b10101100110 #
#383
b11 (
b10101100111 "
b10101100111 $
b10101100111 #
#384
b100 (
b10101101000 "
b10101101000 $
b10101101000 #
#385
b101 (
b10101101001 "
b10101101001 $
b10101101001 #
#386
b110 (
b10101101010 "
b10101101010 $
b10101101010 #
#387
b111 (
b10101101011 "
b10101101011 $
b10101101011 #
#388
b1000 (
b10101101100 "
b10101101100 $
b10101101100 #
#389
b1001 (
b10101101101 "
b10101101101 $
b10101101101 #
#390
b0 (
b1001 '
b10101101110 "
b10101101110 $
b10101101110 #
#391
b1 (
b10101101111 "
b10101101111 $
b10101101111 #
#392
b10 (
b10101110000 "
b10101110000 $
b10101110000 #
#393
b11 (
b10101110001 "
b10101110001 $
b10101110001 #
#394
b100 (
b10101110010 "
b10101110010 $
b10101110010 #
#395
b101 (
b10101110011 "
b10101110011 $
b10101110011 #
#396
b110 (
b10101110100 "
b10101110100 $
b10101110100 #
#397
b111 (
b10101110101 "
b10101110101 $
b10101110101 #
#398
b1000 (
b10101110110 "
b10101110110 $
b10101110110 #
#399
b1001 (
b10101110111 "
b10101110111 $
b10101110111 #
#400
b0 (
b0 '
b100 &
b10101111000 "
b10101111000 $
b10101111000 #
#401
b1 (
b10101111001 "
b10101111001 $
b10101111001 #
#402
b10 (
b10101111010 "
b10101111010 $
b10101111010 #
#403
b11 (
b10101111011 "
b10101111011 $
b10101111011 #
#404
b100 (
b10101111100 "
b10101111100 $
b10101111100 #
#405
b101 (
b10101111101 "
b10101111101 $
b10101111101 #
#406
b110 (
b10101111110 "
b10101111110 $
b10101111110 #
#407
b111 (
b10101111111 "
b10101111111 $
b10101111111 #
#408
b1000 (
b10110000000 "
b10110000000 $
b10110000000 #
#409
b1001 (
b10110000001 "
b10110000001 $
b10110000001 #
#410
b0 (
b1 '
b10110000010 "
b10110000010 $
b10110000010 #
#411
b1 (
b10110000011 "
b10110000011 $
b10110000011 #
#412
b10 (
b10110000100 "
b10110000100 $
b10110000100 #
#413
b11 (
b10110000101 "
b10110000101 $
b10110000101 #
#414
b100 (
b10110000110 "
b10110000110 $
b10110000110 #
#415
b101 (
b10110000111 "
b10110000111 $
b10110000111 #
#416
b110 (
b10110001000 "
b10110001000 $
b10110001000 #
#417
b111 (
b10110001001 "
b10110001001 $
b10110001001 #
#418
b1000 (
b10110001010 "
b10110001010 $
b10110001010 #
#419
b1001 (
b10110001011 "
b10110001011 $
b10110001011 #
#420
b0 (
b10 '
b10110001100 "
b10110001100 $
b10110001100 #
#421
b1 (
b10110001101 "
b10110001101 $
b10110001101 #
#422
b10 (
b10110001110 "
b10110001110 $
b10110001110 #
#423
b11 (
b10110001111 "
b10110001111 $
b10110001111 #
#424
b100 (
b10110010000 "
b10110010000 $
b10110010000 #
#425
b101 (
b10110010001 "
b10110010001 $
b10110010001 #
#426
b110 (
b10110010010 "
b10110010010 $
b10110010010 #
#427
b111 (
b10110010011 "
b10110010011 $
b10110010011 #
#428
b1000 (
b10110010100 "
b10110010100 $
b10110010100 #
#429
b1001 (
b10110010101 "
b10110010101 $
b10110010101 #
#430
b0 (
b11 '
b10110010110 "
b10110010110 $
b10110010110 #
#431
b1 (
b10110010111 "
b10110010111 $
b10110010111 #
#432
b10 (
b10110011000 "
b10110011000 $
b10110011000 #
#433
b11 (
b10110011001 "
b10110011001 $
b10110011001 #
#434
b100 (
b10110011010 "
b10110011010 $
b10110011010 #
