Day 10/counter/ring counter/ringcounter.v
module ringcounter(
input rst,clk,
output reg [3:0]q
);
always @ (posedge clk or posedge rst)begin
	if(rst)q<=4'b0001;
	else q<={q[2:0],q[3]};
end
endmodule

Day 10/counter/ring counter/ringcounter_tb.v
module ringcounter_tb;
reg clk,rst;
wire [3:0]q;
ringcounter dut(.clk(clk),.rst(rst),.q(q));
initial begin
	$monitor("clock = %d | reset = %d | count = %b | time = %0t |",clk,rst,q,$time);
	$dumpfile("ringcounter.vcd");
	$dumpvars(0);

	clk=0;rst=1;#10;


	rst=0;#160
	$finish;

end
always #5 clk=~clk;
endmodule

Day 10/counter/ring counter/ringcounter.vcd
$date
	Thu Dec 18 13:53:17 2025
$end
$version
	Icarus Verilog
$end
$timescale
	1s
$end
$scope module ringcounter_tb $end
$var wire 4 ! q [3:0] $end
$var reg 1 " clk $end
$var reg 1 # rst $end
$scope module dut $end
$var wire 1 " clk $end
$var wire 1 # rst $end
$var reg 4 $ q [3:0] $end
$upscope $end
$upscope $end
$enddefinitions $end
$comment Show the parameter values. $end
$dumpall
$end
#0
$dumpvars
b1 $
1#
0"
b1 !
$end
#5
1"
#10
0"
0#
#15
b10 !
b10 $
1"
#20
0"
#25
b100 !
b100 $
1"
#30
0"
#35
b1000 !
b1000 $
1"
#40
0"
#45
b1 !
b1 $
1"
#50
0"
#55
b10 !
b10 $
1"
#60
0"
#65
b100 !
b100 $
1"
#70
0"
#75
b1000 !
b1000 $
1"
#80
0"
#85
b1 !
b1 $
1"
#90
0"
#95
b10 !
b10 $
1"
#100
0"
#105
b100 !
b100 $
1"
#110
0"
#115
b1000 !
b1000 $
1"
#120
0"
#125
b1 !
b1 $
1"
#130
0"
#135
b10 !
b10 $
1"
#140
0"
#145
b100 !
b100 $
1"
#150
0"
#155
b1000 !
b1000 $
1"
#160
0"
#165
b1 !
b1 $
1"
