Day 09/shift register/piso shift register/piso.v
module piso(
input clk,rst,load,
input [3:0]pin,
output reg sout
);
reg [3:0] shift_reg;

always @(posedge clk) begin
    if (rst) begin
        shift_reg <= 4'b0000;
        sout <= 1'b0;
    end
    else if (load) begin
        shift_reg <= pin;         
    end
    else begin
        sout<= shift_reg[3]; 
        shift_reg <= {shift_reg[2:0], 1'b0}; 
    end
end

endmodule

Day 09/shift register/piso shift register/piso_tb.v
module piso_tb;
reg clk,rst,load;
reg [3:0] pin;
wire sout;
piso dut(.clk(clk),.rst(rst),.load(load),.pin(pin),.sout(sout));
initial begin
$monitor(" clk=%b | rst=%b | load=%b | pin=%b | sout=%b | time = %0t",clk,rst,load,pin,sout,$time);
$dumpfile("piso.vcd");
$dumpvars(0,piso_tb);
clk=0;rst=1;load=0;pin=4'b0000;#5;
rst=0;load=1;pin=4'b1011;#20;
load=0;#80;
$finish;
end
always #10 clk=~clk;
endmodule

Day 09/shift register/piso shift register/piso.vcd
$date
	Mon Dec 15 18:19:01 2025
$end
$version
	Icarus Verilog
$end
$timescale
	1s
$end
$scope module piso_tb $end
$var wire 1 ! sout $end
$var reg 1 " clk $end
$var reg 1 # load $end
$var reg 4 $ pin [3:0] $end
$var reg 1 % rst $end
$scope module dut $end
$var wire 1 " clk $end
$var wire 1 # load $end
$var wire 4 & pin [3:0] $end
$var wire 1 % rst $end
$var reg 4 ' shift_reg [3:0] $end
$var reg 1 ! sout $end
$upscope $end
$upscope $end
$enddefinitions $end
$comment Show the parameter values. $end
$dumpall
$end
#0
$dumpvars
bx '
b0 &
1%
b0 $
0#
0"
x!
$end
#5
b1011 $
b1011 &
1#
0%
#10
b1011 '
1"
#20
0"
#25
0#
#30
b110 '
1!
1"
#40
0"
#50
b1100 '
0!
1"
#60
0"
#70
b1000 '
1!
1"
#80
0"
#90
b0 '
1"
