Day 10/counter/synchronous updown counter/sync_updowncounter.v
module sync_updowncounter(
input clk,rst,mode,
output reg [3:0]q
);
always @ (posedge clk or posedge rst)begin
	if(mode)begin
		if(rst)q<=4'b0000;
		else q<=q+1;
	end
	else if(!mode)begin
		if(rst)q<=4'b1111;
		else q<=q-1;
	end
end
endmodule

Day 10/counter/synchronous updown counter/sync_updowncounter_tb.v
module sync_updowncounter_tb;
reg clk,rst,mode;
wire [3:0]q;
sync_updowncounter dut(.clk(clk),.rst(rst),.mode(mode),.q(q));
initial begin
	$monitor("clock = %d | reset = %d | mode = %d | count = %d | time = %0t |",clk,rst,mode,q,$time);
	$dumpfile("sync_updowncounter.vcd");
	$dumpvars(0);

	clk=0;rst=1;mode=1;#10;


	rst=0;#160;

	rst=1;mode=0;#10;

	rst=0;#160;


	$finish;

end
always #5 clk=~clk;
endmodule

Day 10/counter/synchronous updown counter/sync_updowncounter.vcd
$date
	Thu Dec 18 11:13:01 2025
$end
$version
	Icarus Verilog
$end
$timescale
	1s
$end
$scope module sync_updowncounter_tb $end
$var wire 4 ! q [3:0] $end
$var reg 1 " clk $end
$var reg 1 # mode $end
$var reg 1 $ rst $end
$scope module dut $end
$var wire 1 " clk $end
$var wire 1 # mode $end
$var wire 1 $ rst $end
$var reg 4 % q [3:0] $end
$upscope $end
$upscope $end
$enddefinitions $end
$comment Show the parameter values. $end
$dumpall
$end
#0
$dumpvars
b0 %
1$
1#
0"
b0 !
$end
#5
1"
#10
0"
0$
#15
b1 !
b1 %
1"
#20
0"
#25
b10 !
b10 %
1"
#30
0"
#35
b11 !
b11 %
1"
#40
0"
#45
b100 !
b100 %
1"
#50
0"
#55
b101 !
b101 %
1"
#60
0"
#65
b110 !
b110 %
1"
#70
0"
#75
b111 !
b111 %
1"
#80
0"
#85
b1000 !
b1000 %
1"
#90
0"
#95
b1001 !
b1001 %
1"
#100
0"
#105
b1010 !
b1010 %
1"
#110
0"
#115
b1011 !
b1011 %
1"
#120
0"
#125
b1100 !
b1100 %
1"
#130
0"
#135
b1101 !
b1101 %
1"
#140
0"
#145
b1110 !
b1110 %
1"
#150
0"
#155
b1111 !
b1111 %
1"
#160
0"
#165
b0 !
b0 %
1"
#170
b1111 !
b1111 %
0"
0#
1$
#175
1"
#180
0"
0$
#185
b1110 !
b1110 %
1"
#190
0"
#195
b1101 !
b1101 %
1"
#200
0"
#205
b1100 !
b1100 %
1"
#210
0"
#215
b1011 !
b1011 %
1"
#220
0"
#225
b1010 !
b1010 %
1"
#230
0"
#235
b1001 !
b1001 %
1"
#240
0"
#245
b1000 !
b1000 %
1"
#250
0"
#255
b111 !
b111 %
1"
#260
0"
#265
b110 !
b110 %
1"
#270
0"
#275
b101 !
b101 %
1"
#280
0"
#285
b100 !
b100 %
1"
#290
0"
#295
b11 !
b11 %
1"
#300
0"
#305
b10 !
b10 %
1"
#310
0"
#315
b1 !
b1 %
1"
#320
0"
#325
b0 !
b0 %
1"
#330
0"
#335
b1111 !
b1111 %
1"
