Day 10/counter/asynchronous down counter/async_downcount.v
module tff (input clk, input rst, input t, output reg q);
always @(posedge clk or posedge rst)begin
       	if (rst) q <= 1'b0;
       	else if (t) q <= ~q;
end
endmodule

module async_downcount(
	input clk,rst,
	output [3:0]q
);
tff t0(.clk(clk),.rst(rst),.t(1'b1),.q(q[0]));
tff t1(.clk(q[0]),.rst(rst),.t(1'b1),.q(q[1]));
tff t2(.clk(q[1]),.rst(rst),.t(1'b1),.q(q[2]));
tff t3(.clk(q[2]),.rst(rst),.t(1'b1),.q(q[3]));
endmodule

Day 10/counter/asynchronous down counter/async_downcount_tb.v
module async_downcount_tb;
reg clk,rst;
wire [3:0]q;
async_downcount dut(.clk(clk),.rst(rst),.q(q));
initial begin
	$monitor("clock = %d | reset = %d | output = %d | time = %0t",clk,rst,q,$time);
	$dumpfile("async_downcount.vcd");
	$dumpvars(0);

	clk=0;
	forever #5 clk=~clk;
end

initial begin
	rst=1;

	#10;rst=0;
	#200;$finish;
end
endmodule

Day 10/counter/asynchronous down counter/async_downcount.vcd
$date
	Wed Dec 17 12:37:54 2025
$end
$version
	Icarus Verilog
$end
$timescale
	1s
$end
$scope module async_downcount_tb $end
$var wire 4 ! q [3:0] $end
$var reg 1 " clk $end
$var reg 1 # rst $end
$scope module dut $end
$var wire 1 " clk $end
$var wire 1 # rst $end
$var wire 4 $ q [3:0] $end
$scope module t0 $end
$var wire 1 " clk $end
$var wire 1 # rst $end
$var wire 1 % t $end
$var reg 1 & q $end
$upscope $end
$scope module t1 $end
$var wire 1 ' clk $end
$var wire 1 # rst $end
$var wire 1 ( t $end
$var reg 1 ) q $end
$upscope $end
$scope module t2 $end
$var wire 1 * clk $end
$var wire 1 # rst $end
$var wire 1 + t $end
$var reg 1 , q $end
$upscope $end
$scope module t3 $end
$var wire 1 - clk $end
$var wire 1 # rst $end
$var wire 1 . t $end
$var reg 1 / q $end
$upscope $end
$upscope $end
$upscope $end
$enddefinitions $end
$comment Show the parameter values. $end
$dumpall
$end
#0
$dumpvars
0/
1.
0-
0,
1+
0*
0)
1(
0'
0&
1%
b0 $
1#
0"
b0 !
$end
#5
1"
#10
0"
0#
#15
1/
1-
1,
1*
1)
1'
b1111 !
b1111 $
1&
1"
#20
0"
#25
0'
b1110 !
b1110 $
0&
1"
#30
0"
#35
0*
0)
1'
b1101 !
b1101 $
1&
1"
#40
0"
#45
0'
b1100 !
b1100 $
0&
1"
#50
0"
#55
0-
0,
1*
1)
1'
b1011 !
b1011 $
1&
1"
#60
0"
#65
0'
b1010 !
b1010 $
0&
1"
#70
0"
#75
0*
0)
1'
b1001 !
b1001 $
1&
1"
#80
0"
#85
0'
b1000 !
b1000 $
0&
1"
#90
0"
#95
0/
1-
1,
1*
1)
1'
b111 !
b111 $
1&
1"
#100
0"
#105
0'
b110 !
b110 $
0&
1"
#110
0"
#115
0*
0)
1'
b101 !
b101 $
1&
1"
#120
0"
#125
0'
b100 !
b100 $
0&
1"
#130
0"
#135
0-
0,
1*
1)
1'
b11 !
b11 $
1&
1"
#140
0"
#145
0'
b10 !
b10 $
0&
1"
#150
0"
#155
0*
0)
1'
b1 !
b1 $
1&
1"
#160
0"
#165
0'
b0 !
b0 $
0&
1"
#170
0"
#175
1/
1-
1,
1*
1)
1'
b1111 !
b1111 $
1&
1"
#180
0"
#185
0'
b1110 !
b1110 $
0&
1"
#190
0"
#195
0*
0)
1'
b1101 !
b1101 $
1&
1"
#200
0"
#205
0'
b1100 !
b1100 $
0&
1"
