Day 6/even_parity_checker.v
module even_parity_checker (
    input  [3:0] data,
    input parity,
    output error
);
assign error = ^{data, parity};
endmodule

Day 06/even parity checker/even_parity_checker_tb.v
module even_parity_checker_tb;
reg  [3:0] data;
reg parity;
wire error;
integer i;
even_parity_checker dut (.data(data), .parity(parity),.error(error));
initial begin
    $monitor("time=%0t data=%b parity=%b error=%b", $time, data, parity,error);
    $dumpfile("even_parity_checker.vcd");
    $dumpvars(0);
    data = 4'b0000; parity = 0;#1;
    data = 4'b0001; parity = 1;#1;
    data = 4'b0011; parity = 0;#1;
    data = 4'b0101; parity = 0;#1;
    data = 4'b0110; parity = 1;#1;
    data = 4'b1111; parity = 0;#1;
    data = 4'b1010; parity = 1;#1;
    data = 4'b1101; parity = 1;#1;
    $finish;
   
    end
    endmodule

Day 6/even parity checker/even_parity_checker.vcd
$date
	Sat Dec  6 19:25:07 2025
$end
$version
	Icarus Verilog
$end
$timescale
	1s
$end
$scope module even_parity_checker_tb $end
$var wire 1 ! error $end
$var reg 4 " data [3:0] $end
$var reg 1 # parity $end
$scope module dut $end
$var wire 4 $ data [3:0] $end
$var wire 1 # parity $end
$var wire 1 ! error $end
$upscope $end
$upscope $end
$enddefinitions $end
$comment Show the parameter values. $end
$dumpall
$end
#0
$dumpvars
b0 $
0#
b0 "
0!
$end
#1
1#
0!
b1 "
b1 $
#2
0#
0!
b11 "
b11 $
#3
b101 "
b101 $
#4
1!
1#
b110 "
b110 $
#5
0!
0#
b1111 "
b1111 $
#6
1!
1#
b1010 "
b1010 $
#7
0!
b1101 "
b1101 $
