Day 05/16x1 mux using case statement/mux_16x1.v
//mux
module mux_16x1(
input [3:0]select,
input [15:0]data,
output reg y
);
always @(*) begin
	case(select)
		4'b0000:
			y=data[0];
                4'b0001:
                        y=data[1];
                4'b0010:
                        y=data[2];
                4'b0011:
                        y=data[3];
                4'b0100:
                        y=data[4];
                4'b0101:
                        y=data[5];
                4'b0110:
                        y=data[6];
                4'b0111:
                        y=data[7];
                4'b1000:
                        y=data[8];
                4'b1001:
                        y=data[9];
                4'b1010:
                        y=data[10];
                4'b1011:
                        y=data[11];
                4'b1100:
                        y=data[12];
                4'b1101:
                        y=data[13];
                4'b1110:
                        y=data[14];
                4'b1111:
                        y=data[15];
		default
		y=4'b0000;
	endcase
end
endmodule

day 5/16x1 mux using case statement/mux_16x1_tb.v
module mux_16x1_tb;
reg [15:0]data;
reg [3:0]select;
wire y;
mux_16x1 dut(.data(data),.select(select),.y(y));
initial begin
	$monitor("Time = %0t | data = %b | select = %b | y=%b",$time,data,select,y);
	$dumpfile("mux_16x1.vcd");
	$dumpvars(0);
	data=16'b1010101110101011;
	select=4'd0;#1;
        select=4'd1;#1;
        select=4'd2;#1;
        select=4'd3;#1;
        select=4'd4;#1;
        select=4'd5;#1;
        select=4'd6;#1;
        select=4'd7;#1;
        select=4'd8;#1;
        select=4'd9;#1;
        select=4'd10;#1;
        select=4'd11;#1;
        select=4'd12;#1;
        select=4'd13;#1;
        select=4'd14;#1;
        select=4'd15;#1;
end
endmodule

day 5/16x1 mux using case statement/mux_16x1.vcd
$date
	Fri Dec  5 17:29:13 2025
$end
$version
	Icarus Verilog
$end
$timescale
	1s
$end
$scope module mux_16x1_tb $end
$var wire 1 ! y $end
$var reg 16 " data [15:0] $end
$var reg 4 # select [3:0] $end
$scope module dut $end
$var wire 16 $ data [15:0] $end
$var wire 4 % select [3:0] $end
$var reg 1 ! y $end
$upscope $end
$upscope $end
$enddefinitions $end
$comment Show the parameter values. $end
$dumpall
$end
#0
$dumpvars
b0 %
b1010101110101011 $
b0 #
b1010101110101011 "
1!
$end
#1
b1 #
b1 %
#2
0!
b10 #
b10 %
#3
1!
b11 #
b11 %
#4
0!
b100 #
b100 %
#5
1!
b101 #
b101 %
#6
0!
b110 #
b110 %
#7
1!
b111 #
b111 %
#8
b1000 #
b1000 %
#9
b1001 #
b1001 %
#10
0!
b1010 #
b1010 %
#11
1!
b1011 #
b1011 %
#12
0!
b1100 #
b1100 %
#13
1!
b1101 #
b1101 %
#14
0!
b1110 #
b1110 %
#15
1!
b1111 #
b1111 %
