Day 09/shift register/siso shift register/siso.v
module siso (
    input  clk,
    input  rst,
    input  sin,
    output sout
);

reg [3:0] shift_reg;

always @(posedge clk) begin
    if (rst)
        shift_reg <= 4'b0000;
    else
        shift_reg <= {shift_reg[2:0], sin};
end

assign sout = shift_reg[3];

endmodule

Day 09/shift register/siso shift register/siso_tb.v
module siso_tb;

reg clk;
reg rst;
reg sin;
wire sout;

siso dut (
    .clk(clk),
    .rst(rst),
    .sin(sin),
    .sout(sout)
);

initial begin
    $monitor("time=%0t | rst=%b | sin=%b | sout=%b", $time, rst, sin, sout);
    $dumpfile("siso.vcd");
    $dumpvars(0, siso_tb);

   
    clk = 0;
    rst = 1;
    sin = 0;
    #5;

   
    rst = 0;

    // Apply serial data: 1 0 1 1
    #10 sin = 1;
    #20 sin = 0;
    #20 sin = 1;
    #20 sin = 1;

   
    #20 $finish;
end

always #10 clk = ~clk;

endmodule

Day 09/shift register/siso shift register/siso.vcd
$date
	Mon Dec 15 15:27:48 2025
$end
$version
	Icarus Verilog
$end
$timescale
	1s
$end
$scope module siso_tb $end
$var wire 1 ! sout $end
$var reg 1 " clk $end
$var reg 1 # rst $end
$var reg 1 $ sin $end
$scope module dut $end
$var wire 1 " clk $end
$var wire 1 # rst $end
$var wire 1 $ sin $end
$var wire 1 ! sout $end
$var reg 4 % shift_reg [3:0] $end
$upscope $end
$upscope $end
$enddefinitions $end
$comment Show the parameter values. $end
$dumpall
$end
#0
$dumpvars
bx %
0$
1#
0"
x!
$end
#5
0#
#10
bx0 %
1"
#15
1$
#20
0"
#30
bx01 %
1"
#35
0$
#40
0"
#50
bx010 %
1"
#55
1$
#60
0"
#70
0!
b101 %
1"
#80
0"
#90
1!
b1011 %
1"
