Day 03/Priority Encoder/priority_encoder.v
module priority_encoder(output a,b, input d0,d1,d2,d3);
assign a = d2|d3;
assign b = d3|(~d2&d1);
endmodule

Day3/Priority Encoder/priority_encoder_tb.v
module priority_encoder_tb;
reg d0,d1,d2,d3;
wire a,b;
priority_encoder dut(.a(a),.b(b),.d0(d0),.d1(d1),.d2(d2),.d3(d3));
initial begin
	$monitor("Time = %t | d3 = %b |d2 = %b | d1 = %b | d0 = %b | a = %b | b = %b |",$time,d3,d2,d1,d0,a,b);
	$dumpfile("priority_encoder.vcd");
	$dumpvars(0);
	d3=0;d2=0;d1=0;d0=0;#10;
	d3=0;d2=0;d1=0;d0=1;#10;
	d3=0;d2=0;d1=1;d0=0;#10;
	d3=0;d2=0;d1=1;d0=1;#10;
	d3=0;d2=1;d1=0;d0=0;#10;
	d3=0;d2=1;d1=0;d0=1;#10;
	d3=0;d2=1;d1=1;d0=0;#10;
	d3=0;d2=1;d1=1;d0=1;#10;
	d3=1;d2=0;d1=0;d0=0;#10;
	d3=1;d2=0;d1=0;d0=1;#10;
	d3=1;d2=0;d1=1;d0=0;#10;
	d3=1;d2=0;d1=1;d0=1;#10;
	d3=1;d2=1;d1=0;d0=0;#10;
	d3=1;d2=1;d1=0;d0=1;#10; 
	d3=1;d2=1;d1=1;d0=0;#10;
	d3=1;d2=1;d1=1;d0=1;#10;
	$finish;
end
endmodule

Day3/Priority Encoder/priority_encoder.vcd
$date
	Wed Dec  3 13:27:09 2025
$end
$version
	Icarus Verilog
$end
$timescale
	1s
$end
$scope module priority_encoder_tb $end
$var wire 1 ! b $end
$var wire 1 " a $end
$var reg 1 # d0 $end
$var reg 1 $ d1 $end
$var reg 1 % d2 $end
$var reg 1 & d3 $end
$scope module dut $end
$var wire 1 " a $end
$var wire 1 ! b $end
$var wire 1 # d0 $end
$var wire 1 $ d1 $end
$var wire 1 % d2 $end
$var wire 1 & d3 $end
$upscope $end
$upscope $end
$enddefinitions $end
$comment Show the parameter values. $end
$dumpall
$end
#0
$dumpvars
0&
0%
0$
0#
0"
0!
$end
#10
1#
#20
1!
0#
1$
#30
1#
#40
0!
1"
0#
0$
1%
#50
1#
#60
0#
1$
#70
1#
#80
1!
0#
0$
0%
1&
#90
1#
#100
0#
1$
#110
1#
#120
0#
0$
1%
#130
1#
#140
0#
1$
#150
1#
