Day 6/gray_binary.v
module gray_to_binary (
    input  [3:0] gray,
    output [3:0] bin
);
assign bin[3] = gray[3];
assign bin[2] = bin[3] ^ gray[2];
assign bin[1] = bin[2] ^ gray[1];
assign bin[0] = bin[1] ^ gray[0];
endmodule

Day 6/gray to binary/gray_to_binary_tb.v
module binary_to_gray_tb;
reg  [3:0] gray;
wire [3:0] bin;
integer i;
gray_to_binary dut (.bin(bin), .gray(gray));
initial begin
    $monitor("time=%0t gray=%b binary=%b", $time, gray, bin);
    $dumpfile("gray_to_binary.vcd");
    $dumpvars(0);
    for(i=0;i<16;i=i+1)begin
	    gray=i;#1;
    end
    end
    endmodule

Day 6/gray to binary/gray_to_binary.vcd
$date
	Sat Dec  6 18:42:13 2025
$end
$version
	Icarus Verilog
$end
$timescale
	1s
$end
$scope module binary_to_gray_tb $end
$var wire 4 ! bin [3:0] $end
$var reg 4 " gray [3:0] $end
$var integer 32 # i [31:0] $end
$scope module dut $end
$var wire 4 $ gray [3:0] $end
$var wire 4 % bin [3:0] $end
$upscope $end
$upscope $end
$enddefinitions $end
$comment Show the parameter values. $end
$dumpall
$end
#0
$dumpvars
b0 %
b0 $
b0 #
b0 "
b0 !
$end
#1
b1 !
b1 %
b1 "
b1 $
b1 #
#2
b11 !
b11 %
b10 "
b10 $
b10 #
#3
b10 !
b10 %
b11 "
b11 $
b11 #
#4
b111 !
b111 %
b100 "
b100 $
b100 #
#5
b110 !
b110 %
b101 "
b101 $
b101 #
#6
b100 !
b100 %
b110 "
b110 $
b110 #
#7
b101 !
b101 %
b111 "
b111 $
b111 #
#8
b1111 !
b1111 %
b1000 "
b1000 $
b1000 #
#9
b1110 !
b1110 %
b1001 "
b1001 $
b1001 #
#10
b1100 !
b1100 %
b1010 "
b1010 $
b1010 #
#11
b1101 !
b1101 %
b1011 "
b1011 $
b1011 #
#12
b1000 !
b1000 %
b1100 "
b1100 $
b1100 #
#13
b1001 !
b1001 %
b1101 "
b1101 $
b1101 #
#14
b1011 !
b1011 %
b1110 "
b1110 $
b1110 #
#15
b1010 !
b1010 %
b1111 "
b1111 $
b1111 #
#16
b10000 #
